setup.py
hladny_matfyzak.egg-info/PKG-INFO
hladny_matfyzak.egg-info/SOURCES.txt
hladny_matfyzak.egg-info/dependency_links.txt
hladny_matfyzak.egg-info/requires.txt
hladny_matfyzak.egg-info/top_level.txt
hladnymatfyzak/__init__.py