Metadata-Version: 1.1
Name: hladny-matfyzak
Version: 0.0.6.1
Summary: Python parsing functions for hungry students in Bratislava
Home-page: https://github.com/hladny-matfyzak/py-hladny-matfyzak
Author: Wido
Author-email: tomas.wido@gmail.com
License: MIT
Platform: UNKNOWN
Classifier: Development Status :: 3 - Alpha
Classifier: Intended Audience :: Developers
